image_generator-1.1.3.data/scripts/image-generator
image_generator-1.1.3.dist-info/DESCRIPTION.rst
image_generator-1.1.3.dist-info/METADATA
image_generator-1.1.3.dist-info/RECORD
image_generator-1.1.3.dist-info/WHEEL
image_generator-1.1.3.dist-info/metadata.json
image_generator-1.1.3.dist-info/top_level.txt
openbaton/__init__.py
openbaton/errors.py
openbaton/main.py
openbaton/utils.py
tests/__init__.py
tests/test_methods.py
