Metadata-Version: 1.1
Name: image-generator
Version: 1.1.3
Summary: The Image Generator
Home-page: http://openbaton.org/
Author: Open Baton Dev
Author-email: dev@openbaton.org
License: Apache 2
Keywords: python vnfm nfvo lxc open baton openbaton sdk lxd
Platform: UNKNOWN
Classifier: Intended Audience :: Developers
Classifier: Programming Language :: Python :: 3.5
Classifier: License :: OSI Approved :: Apache Software License
